modis_tools/__init__.py
modis_tools/api.py
modis_tools/auth.py
modis_tools/decorators.py
modis_tools/granule_handler.py
modis_tools/models.py
modis_tools/request_helpers.py
modis_tools/resources.py
modis_tools/constants/__init__.py
modis_tools/constants/mimetypes.py
modis_tools/constants/urls.py
modis_tools-2.0.1.dist-info/licenses/LICENSE
tests/__init__.py
tests/test_api.py
tests/test_auth.py
tests/test_models.py
tests/test_request_helpers.py
modis_tools-2.0.1.dist-info/METADATA
modis_tools-2.0.1.dist-info/WHEEL
modis_tools-2.0.1.dist-info/top_level.txt
modis_tools-2.0.1.dist-info/RECORD
