Metadata-Version: 2.4
Name: modis_tools
Version: 2.0.1
Summary: Tools for working with the MODIS API and MODIS data.
Home-page: https://github.com/fraymio/modis-tools.git
Author: fraym
Author-email: datascience@fraym.io
Classifier: Development Status :: 5 - Production/Stable
Classifier: Programming Language :: Python :: 3.7
Classifier: Operating System :: OS Independent
Requires-Python: >=3.7
License-File: LICENSE
Requires-Dist: requests==2.*
Requires-Dist: pydantic==2.*
Requires-Dist: python-dateutil==2.*
Requires-Dist: shapely==2.*
Requires-Dist: tqdm>=4.42.0
Requires-Dist: setuptools==69.2.0
Provides-Extra: test
Requires-Dist: pytest; extra == "test"
Provides-Extra: gdal
Requires-Dist: gdal; extra == "gdal"
Dynamic: author
Dynamic: author-email
Dynamic: classifier
Dynamic: description
Dynamic: description-content-type
Dynamic: home-page
Dynamic: license-file
Dynamic: provides-extra
Dynamic: requires-dist
Dynamic: requires-python
Dynamic: summary
